HarfangHighLevel/LOD_Manager.py
HarfangHighLevel/__init__.py
HarfangHighLevel/Harfang/resources.7z
HarfangHighLevel/Harfang/_bin/assetc.exe
HarfangHighLevel/Harfang/_bin/assimp_converter.exe
HarfangHighLevel/Harfang/_bin/fbx_converter.exe
HarfangHighLevel/Harfang/_bin/glfw3.dll
HarfangHighLevel/Harfang/_bin/gltf_exporter.exe
HarfangHighLevel/Harfang/_bin/gltf_importer.exe
HarfangHighLevel/Harfang/_bin/libfbxsdk.dll
HarfangHighLevel/Harfang/_bin/lua54.dll
HarfangHighLevel/Harfang/_bin/openvr_api.dll
HarfangHighLevel/Harfang/_bin/toolchains/host-windows-x64-target-windows-x64/cmft.exe
HarfangHighLevel/Harfang/_bin/toolchains/host-windows-x64-target-windows-x64/luac.exe
HarfangHighLevel/Harfang/_bin/toolchains/host-windows-x64-target-windows-x64/recastc.exe
HarfangHighLevel/Harfang/_bin/toolchains/host-windows-x64-target-windows-x64/shaderc.exe
HarfangHighLevel/Harfang/_bin/toolchains/host-windows-x64-target-windows-x64/texconv.exe
HarfangHighLevel/Harfang/_bin/toolchains/host-windows-x64-target-windows-x64/texturec.exe
HarfangHighLevel-3.2.4.dist-info/METADATA
HarfangHighLevel-3.2.4.dist-info/WHEEL
HarfangHighLevel-3.2.4.dist-info/top_level.txt
HarfangHighLevel-3.2.4.dist-info/RECORD
