Metadata-Version: 2.1
Name: HarfangHighLevel
Version: 3.2.4
Summary: High Level functions to use with Harfang
Home-page: https://www.harfang3d.com
Author: NWNC HARFANG
Author-email: contact@harfang3d.com
License: Other/Proprietary License
Keywords: 2d 3d multimedia development engine realtime rendering design visualization simulation physics vr virtual reality python lua opengl opengles directx
Classifier: Intended Audience :: Developers
Classifier: Topic :: Software Development
Classifier: Topic :: Software Development :: Libraries :: Application Frameworks
Classifier: Topic :: Multimedia :: Sound/Audio
Classifier: Topic :: Multimedia :: Graphics :: 3D Rendering
Classifier: Topic :: Scientific/Engineering :: Visualization
Classifier: Operating System :: Microsoft
Classifier: Operating System :: Microsoft :: Windows
Classifier: Programming Language :: Python :: 3
Requires-Python: >=3.8
Requires-Dist: harfang (==3.2.4)
Requires-Dist: tqdm
Requires-Dist: py7zr
